[
    {
        "label": "Flask",
        "importPath": "flask",
        "description": "flask",
        "isExtraImport": true,
        "detail": "flask",
        "documentation": {}
    },
    {
        "label": "jsonify",
        "importPath": "flask",
        "description": "flask",
        "isExtraImport": true,
        "detail": "flask",
        "documentation": {}
    },
    {
        "label": "request",
        "importPath": "flask",
        "description": "flask",
        "isExtraImport": true,
        "detail": "flask",
        "documentation": {}
    },
    {
        "label": "JWTManager",
        "importPath": "flask_jwt_extended",
        "description": "flask_jwt_extended",
        "isExtraImport": true,
        "detail": "flask_jwt_extended",
        "documentation": {}
    },
    {
        "label": "create_access_token",
        "importPath": "flask_jwt_extended",
        "description": "flask_jwt_extended",
        "isExtraImport": true,
        "detail": "flask_jwt_extended",
        "documentation": {}
    },
    {
        "label": "jwt_required",
        "importPath": "flask_jwt_extended",
        "description": "flask_jwt_extended",
        "isExtraImport": true,
        "detail": "flask_jwt_extended",
        "documentation": {}
    },
    {
        "label": "get_jwt_identity",
        "importPath": "flask_jwt_extended",
        "description": "flask_jwt_extended",
        "isExtraImport": true,
        "detail": "flask_jwt_extended",
        "documentation": {}
    },
    {
        "label": "json",
        "kind": 6,
        "isExtraImport": true,
        "importPath": "json",
        "description": "json",
        "detail": "json",
        "documentation": {}
    },
    {
        "label": "stringify",
        "importPath": "flatted",
        "description": "flatted",
        "isExtraImport": true,
        "detail": "flatted",
        "documentation": {}
    },
    {
        "label": "parse",
        "importPath": "flatted",
        "description": "flatted",
        "isExtraImport": true,
        "detail": "flatted",
        "documentation": {}
    },
    {
        "label": "login",
        "kind": 2,
        "importPath": "api.index",
        "description": "api.index",
        "peekOfCode": "def login():\n    auth = request.get_json()\n    user = next((u for u in users if u['username'] == auth['username'] and u['password'] == auth['password']), None)\n    if user:\n        access_token = create_access_token(identity=user)\n        return jsonify({'access_token': access_token}), 200\n    return jsonify({'message': 'Invalid credentials'}), 401\n# Dummy endpoint accessible without authentication\n@app.route('/api/python')\ndef hello_world():",
        "detail": "api.index",
        "documentation": {}
    },
    {
        "label": "hello_world",
        "kind": 2,
        "importPath": "api.index",
        "description": "api.index",
        "peekOfCode": "def hello_world():\n    return \"<p>Hello, World!</p>\"\n# Protected endpoint example\n@app.route('/api/protected')\n@jwt_required()\ndef protected():\n    current_user = get_jwt_identity()\n    return jsonify(logged_in_as=current_user), 200\nif __name__ == '__main__':\n    app.run(debug=True)",
        "detail": "api.index",
        "documentation": {}
    },
    {
        "label": "protected",
        "kind": 2,
        "importPath": "api.index",
        "description": "api.index",
        "peekOfCode": "def protected():\n    current_user = get_jwt_identity()\n    return jsonify(logged_in_as=current_user), 200\nif __name__ == '__main__':\n    app.run(debug=True)",
        "detail": "api.index",
        "documentation": {}
    },
    {
        "label": "app",
        "kind": 5,
        "importPath": "api.index",
        "description": "api.index",
        "peekOfCode": "app = Flask(__name__)\napp.config['JWT_SECRET_KEY'] = 'your-secret-key'  # Change this to a secure key in production\njwt = JWTManager(app)\n# Dummy database for demonstration purposes\nusers = [\n    {'username': 'admin', 'password': 'admin', 'role': 'adm'},\n    {'username': 'client1', 'password': 'password1', 'role': 'client'},\n    {'username': 'client2', 'password': 'password2', 'role': 'client'}\n]\nuniverses = [",
        "detail": "api.index",
        "documentation": {}
    },
    {
        "label": "app.config['JWT_SECRET_KEY']",
        "kind": 5,
        "importPath": "api.index",
        "description": "api.index",
        "peekOfCode": "app.config['JWT_SECRET_KEY'] = 'your-secret-key'  # Change this to a secure key in production\njwt = JWTManager(app)\n# Dummy database for demonstration purposes\nusers = [\n    {'username': 'admin', 'password': 'admin', 'role': 'adm'},\n    {'username': 'client1', 'password': 'password1', 'role': 'client'},\n    {'username': 'client2', 'password': 'password2', 'role': 'client'}\n]\nuniverses = [\n    {'id': 1, 'name': 'Universe 1'},",
        "detail": "api.index",
        "documentation": {}
    },
    {
        "label": "jwt",
        "kind": 5,
        "importPath": "api.index",
        "description": "api.index",
        "peekOfCode": "jwt = JWTManager(app)\n# Dummy database for demonstration purposes\nusers = [\n    {'username': 'admin', 'password': 'admin', 'role': 'adm'},\n    {'username': 'client1', 'password': 'password1', 'role': 'client'},\n    {'username': 'client2', 'password': 'password2', 'role': 'client'}\n]\nuniverses = [\n    {'id': 1, 'name': 'Universe 1'},\n    {'id': 2, 'name': 'Universe 2'}",
        "detail": "api.index",
        "documentation": {}
    },
    {
        "label": "users",
        "kind": 5,
        "importPath": "api.index",
        "description": "api.index",
        "peekOfCode": "users = [\n    {'username': 'admin', 'password': 'admin', 'role': 'adm'},\n    {'username': 'client1', 'password': 'password1', 'role': 'client'},\n    {'username': 'client2', 'password': 'password2', 'role': 'client'}\n]\nuniverses = [\n    {'id': 1, 'name': 'Universe 1'},\n    {'id': 2, 'name': 'Universe 2'}\n]\n# Authentication endpoint",
        "detail": "api.index",
        "documentation": {}
    },
    {
        "label": "universes",
        "kind": 5,
        "importPath": "api.index",
        "description": "api.index",
        "peekOfCode": "universes = [\n    {'id': 1, 'name': 'Universe 1'},\n    {'id': 2, 'name': 'Universe 2'}\n]\n# Authentication endpoint\n@app.route('/api/login', methods=['POST'])\ndef login():\n    auth = request.get_json()\n    user = next((u for u in users if u['username'] == auth['username'] and u['password'] == auth['password']), None)\n    if user:",
        "detail": "api.index",
        "documentation": {}
    },
    {
        "label": "_Known",
        "kind": 6,
        "importPath": "node_modules.flatted.python.flatted",
        "description": "node_modules.flatted.python.flatted",
        "peekOfCode": "class _Known:\n    def __init__(self):\n        self.key = []\n        self.value = []\nclass _String:\n    def __init__(self, value):\n        self.value = value\ndef _array_keys(value):\n    keys = []\n    i = 0",
        "detail": "node_modules.flatted.python.flatted",
        "documentation": {}
    },
    {
        "label": "_String",
        "kind": 6,
        "importPath": "node_modules.flatted.python.flatted",
        "description": "node_modules.flatted.python.flatted",
        "peekOfCode": "class _String:\n    def __init__(self, value):\n        self.value = value\ndef _array_keys(value):\n    keys = []\n    i = 0\n    for _ in value:\n        keys.append(i)\n        i += 1\n    return keys",
        "detail": "node_modules.flatted.python.flatted",
        "documentation": {}
    },
    {
        "label": "parse",
        "kind": 2,
        "importPath": "node_modules.flatted.python.flatted",
        "description": "node_modules.flatted.python.flatted",
        "peekOfCode": "def parse(value, *args, **kwargs):\n    json = _json.loads(value, *args, **kwargs)\n    wrapped = []\n    for value in json:\n        wrapped.append(_wrap(value))\n    input = []\n    for value in wrapped:\n        if isinstance(value, _String):\n            input.append(value.value)\n        else:",
        "detail": "node_modules.flatted.python.flatted",
        "documentation": {}
    },
    {
        "label": "stringify",
        "kind": 2,
        "importPath": "node_modules.flatted.python.flatted",
        "description": "node_modules.flatted.python.flatted",
        "peekOfCode": "def stringify(value, *args, **kwargs):\n    known = _Known()\n    input = []\n    output = []\n    i = int(_index(known, input, value))\n    while i < len(input):\n        output.append(_transform(known, input, input[i]))\n        i += 1\n    return _json.dumps(output, *args, **kwargs)",
        "detail": "node_modules.flatted.python.flatted",
        "documentation": {}
    },
    {
        "label": "stringify",
        "kind": 2,
        "importPath": "node_modules.flatted.python.test",
        "description": "node_modules.flatted.python.test",
        "peekOfCode": "def stringify(value):\n    return _stringify(value, separators=(',', ':'))\nassert stringify([None, None]) == '[[null,null]]'\na = []\no = {}\nassert stringify(a) == '[[]]'\nassert stringify(o) == '[{}]'\na.append(a)\no['o'] = o\nassert stringify(a) == '[[\"0\"]]'",
        "detail": "node_modules.flatted.python.test",
        "documentation": {}
    },
    {
        "label": "a",
        "kind": 5,
        "importPath": "node_modules.flatted.python.test",
        "description": "node_modules.flatted.python.test",
        "peekOfCode": "a = []\no = {}\nassert stringify(a) == '[[]]'\nassert stringify(o) == '[{}]'\na.append(a)\no['o'] = o\nassert stringify(a) == '[[\"0\"]]'\nassert stringify(o) == '[{\"o\":\"0\"}]'\nb = parse(stringify(a))\nassert isinstance(b, list) and b[0] == b",
        "detail": "node_modules.flatted.python.test",
        "documentation": {}
    },
    {
        "label": "o",
        "kind": 5,
        "importPath": "node_modules.flatted.python.test",
        "description": "node_modules.flatted.python.test",
        "peekOfCode": "o = {}\nassert stringify(a) == '[[]]'\nassert stringify(o) == '[{}]'\na.append(a)\no['o'] = o\nassert stringify(a) == '[[\"0\"]]'\nassert stringify(o) == '[{\"o\":\"0\"}]'\nb = parse(stringify(a))\nassert isinstance(b, list) and b[0] == b\na.append(1)",
        "detail": "node_modules.flatted.python.test",
        "documentation": {}
    },
    {
        "label": "o['o']",
        "kind": 5,
        "importPath": "node_modules.flatted.python.test",
        "description": "node_modules.flatted.python.test",
        "peekOfCode": "o['o'] = o\nassert stringify(a) == '[[\"0\"]]'\nassert stringify(o) == '[{\"o\":\"0\"}]'\nb = parse(stringify(a))\nassert isinstance(b, list) and b[0] == b\na.append(1)\na.append('two')\na.append(True)\no['one'] = 1\no['two'] = 'two'",
        "detail": "node_modules.flatted.python.test",
        "documentation": {}
    },
    {
        "label": "b",
        "kind": 5,
        "importPath": "node_modules.flatted.python.test",
        "description": "node_modules.flatted.python.test",
        "peekOfCode": "b = parse(stringify(a))\nassert isinstance(b, list) and b[0] == b\na.append(1)\na.append('two')\na.append(True)\no['one'] = 1\no['two'] = 'two'\no['three'] = True\nassert stringify(a) == '[[\"0\",1,\"1\",true],\"two\"]'\nassert stringify(o) == '[{\"o\":\"0\",\"one\":1,\"two\":\"1\",\"three\":true},\"two\"]'",
        "detail": "node_modules.flatted.python.test",
        "documentation": {}
    },
    {
        "label": "o['one']",
        "kind": 5,
        "importPath": "node_modules.flatted.python.test",
        "description": "node_modules.flatted.python.test",
        "peekOfCode": "o['one'] = 1\no['two'] = 'two'\no['three'] = True\nassert stringify(a) == '[[\"0\",1,\"1\",true],\"two\"]'\nassert stringify(o) == '[{\"o\":\"0\",\"one\":1,\"two\":\"1\",\"three\":true},\"two\"]'\na.append(o)\no['a'] = a\nassert stringify(a) == '[[\"0\",1,\"1\",true,\"2\"],\"two\",{\"o\":\"2\",\"one\":1,\"two\":\"1\",\"three\":true,\"a\":\"0\"}]'\nassert stringify(o) == '[{\"o\":\"0\",\"one\":1,\"two\":\"1\",\"three\":true,\"a\":\"2\"},\"two\",[\"2\",1,\"1\",true,\"0\"]]'\na.append({'test': 'OK'})",
        "detail": "node_modules.flatted.python.test",
        "documentation": {}
    },
    {
        "label": "o['two']",
        "kind": 5,
        "importPath": "node_modules.flatted.python.test",
        "description": "node_modules.flatted.python.test",
        "peekOfCode": "o['two'] = 'two'\no['three'] = True\nassert stringify(a) == '[[\"0\",1,\"1\",true],\"two\"]'\nassert stringify(o) == '[{\"o\":\"0\",\"one\":1,\"two\":\"1\",\"three\":true},\"two\"]'\na.append(o)\no['a'] = a\nassert stringify(a) == '[[\"0\",1,\"1\",true,\"2\"],\"two\",{\"o\":\"2\",\"one\":1,\"two\":\"1\",\"three\":true,\"a\":\"0\"}]'\nassert stringify(o) == '[{\"o\":\"0\",\"one\":1,\"two\":\"1\",\"three\":true,\"a\":\"2\"},\"two\",[\"2\",1,\"1\",true,\"0\"]]'\na.append({'test': 'OK'})\na.append([1, 2, 3])",
        "detail": "node_modules.flatted.python.test",
        "documentation": {}
    },
    {
        "label": "o['three']",
        "kind": 5,
        "importPath": "node_modules.flatted.python.test",
        "description": "node_modules.flatted.python.test",
        "peekOfCode": "o['three'] = True\nassert stringify(a) == '[[\"0\",1,\"1\",true],\"two\"]'\nassert stringify(o) == '[{\"o\":\"0\",\"one\":1,\"two\":\"1\",\"three\":true},\"two\"]'\na.append(o)\no['a'] = a\nassert stringify(a) == '[[\"0\",1,\"1\",true,\"2\"],\"two\",{\"o\":\"2\",\"one\":1,\"two\":\"1\",\"three\":true,\"a\":\"0\"}]'\nassert stringify(o) == '[{\"o\":\"0\",\"one\":1,\"two\":\"1\",\"three\":true,\"a\":\"2\"},\"two\",[\"2\",1,\"1\",true,\"0\"]]'\na.append({'test': 'OK'})\na.append([1, 2, 3])\no['test'] = {'test': 'OK'}",
        "detail": "node_modules.flatted.python.test",
        "documentation": {}
    },
    {
        "label": "o['a']",
        "kind": 5,
        "importPath": "node_modules.flatted.python.test",
        "description": "node_modules.flatted.python.test",
        "peekOfCode": "o['a'] = a\nassert stringify(a) == '[[\"0\",1,\"1\",true,\"2\"],\"two\",{\"o\":\"2\",\"one\":1,\"two\":\"1\",\"three\":true,\"a\":\"0\"}]'\nassert stringify(o) == '[{\"o\":\"0\",\"one\":1,\"two\":\"1\",\"three\":true,\"a\":\"2\"},\"two\",[\"2\",1,\"1\",true,\"0\"]]'\na.append({'test': 'OK'})\na.append([1, 2, 3])\no['test'] = {'test': 'OK'}\no['array'] = [1, 2, 3]\nassert stringify(a) == '[[\"0\",1,\"1\",true,\"2\",\"3\",\"4\"],\"two\",{\"o\":\"2\",\"one\":1,\"two\":\"1\",\"three\":true,\"a\":\"0\",\"test\":\"3\",\"array\":\"4\"},{\"test\":\"5\"},[1,2,3],\"OK\"]'\nassert stringify(o) == '[{\"o\":\"0\",\"one\":1,\"two\":\"1\",\"three\":true,\"a\":\"2\",\"test\":\"3\",\"array\":\"4\"},\"two\",[\"2\",1,\"1\",true,\"0\",\"3\",\"4\"],{\"test\":\"5\"},[1,2,3],\"OK\"]'\na2 = parse(stringify(a));",
        "detail": "node_modules.flatted.python.test",
        "documentation": {}
    },
    {
        "label": "o['test']",
        "kind": 5,
        "importPath": "node_modules.flatted.python.test",
        "description": "node_modules.flatted.python.test",
        "peekOfCode": "o['test'] = {'test': 'OK'}\no['array'] = [1, 2, 3]\nassert stringify(a) == '[[\"0\",1,\"1\",true,\"2\",\"3\",\"4\"],\"two\",{\"o\":\"2\",\"one\":1,\"two\":\"1\",\"three\":true,\"a\":\"0\",\"test\":\"3\",\"array\":\"4\"},{\"test\":\"5\"},[1,2,3],\"OK\"]'\nassert stringify(o) == '[{\"o\":\"0\",\"one\":1,\"two\":\"1\",\"three\":true,\"a\":\"2\",\"test\":\"3\",\"array\":\"4\"},\"two\",[\"2\",1,\"1\",true,\"0\",\"3\",\"4\"],{\"test\":\"5\"},[1,2,3],\"OK\"]'\na2 = parse(stringify(a));\no2 = parse(stringify(o));\nassert a2[0] == a2\nassert o2['o'] == o2\nassert a2[1] == 1 and a2[2] == 'two' and a2[3] == True and isinstance(a2[4], dict)\nassert a2[4] == a2[4]['o'] and a2 == a2[4]['o']['a']",
        "detail": "node_modules.flatted.python.test",
        "documentation": {}
    },
    {
        "label": "o['array']",
        "kind": 5,
        "importPath": "node_modules.flatted.python.test",
        "description": "node_modules.flatted.python.test",
        "peekOfCode": "o['array'] = [1, 2, 3]\nassert stringify(a) == '[[\"0\",1,\"1\",true,\"2\",\"3\",\"4\"],\"two\",{\"o\":\"2\",\"one\":1,\"two\":\"1\",\"three\":true,\"a\":\"0\",\"test\":\"3\",\"array\":\"4\"},{\"test\":\"5\"},[1,2,3],\"OK\"]'\nassert stringify(o) == '[{\"o\":\"0\",\"one\":1,\"two\":\"1\",\"three\":true,\"a\":\"2\",\"test\":\"3\",\"array\":\"4\"},\"two\",[\"2\",1,\"1\",true,\"0\",\"3\",\"4\"],{\"test\":\"5\"},[1,2,3],\"OK\"]'\na2 = parse(stringify(a));\no2 = parse(stringify(o));\nassert a2[0] == a2\nassert o2['o'] == o2\nassert a2[1] == 1 and a2[2] == 'two' and a2[3] == True and isinstance(a2[4], dict)\nassert a2[4] == a2[4]['o'] and a2 == a2[4]['o']['a']\nstr = parse('[{\"prop\":\"1\",\"a\":\"2\",\"b\":\"3\"},{\"value\":123},[\"4\",\"5\"],{\"e\":\"6\",\"t\":\"7\",\"p\":4},{},{\"b\":\"8\"},\"f\",{\"a\":\"9\"},[\"10\"],\"sup\",{\"a\":1,\"d\":2,\"c\":\"7\",\"z\":\"11\",\"h\":1},{\"g\":2,\"a\":\"7\",\"b\":\"12\",\"f\":6},{\"r\":4,\"u\":\"7\",\"c\":5}]')",
        "detail": "node_modules.flatted.python.test",
        "documentation": {}
    },
    {
        "label": "a2",
        "kind": 5,
        "importPath": "node_modules.flatted.python.test",
        "description": "node_modules.flatted.python.test",
        "peekOfCode": "a2 = parse(stringify(a));\no2 = parse(stringify(o));\nassert a2[0] == a2\nassert o2['o'] == o2\nassert a2[1] == 1 and a2[2] == 'two' and a2[3] == True and isinstance(a2[4], dict)\nassert a2[4] == a2[4]['o'] and a2 == a2[4]['o']['a']\nstr = parse('[{\"prop\":\"1\",\"a\":\"2\",\"b\":\"3\"},{\"value\":123},[\"4\",\"5\"],{\"e\":\"6\",\"t\":\"7\",\"p\":4},{},{\"b\":\"8\"},\"f\",{\"a\":\"9\"},[\"10\"],\"sup\",{\"a\":1,\"d\":2,\"c\":\"7\",\"z\":\"11\",\"h\":1},{\"g\":2,\"a\":\"7\",\"b\":\"12\",\"f\":6},{\"r\":4,\"u\":\"7\",\"c\":5}]')\nassert str['b']['t']['a'] == 'sup' and str['a'][1]['b'][0]['c'] == str['b']['t']\noo = parse('[{\"a\":\"1\",\"b\":\"0\",\"c\":\"2\"},{\"aa\":\"3\"},{\"ca\":\"4\",\"cb\":\"5\",\"cc\":\"6\",\"cd\":\"7\",\"ce\":\"8\",\"cf\":\"9\"},{\"aaa\":\"10\"},{\"caa\":\"4\"},{\"cba\":\"5\"},{\"cca\":\"2\"},{\"cda\":\"4\"},\"value2\",\"value3\",\"value1\"]');\nassert oo['a']['aa']['aaa'] == 'value1' and oo == oo['b'] and oo['c']['ca']['caa'] == oo['c']['ca']",
        "detail": "node_modules.flatted.python.test",
        "documentation": {}
    },
    {
        "label": "o2",
        "kind": 5,
        "importPath": "node_modules.flatted.python.test",
        "description": "node_modules.flatted.python.test",
        "peekOfCode": "o2 = parse(stringify(o));\nassert a2[0] == a2\nassert o2['o'] == o2\nassert a2[1] == 1 and a2[2] == 'two' and a2[3] == True and isinstance(a2[4], dict)\nassert a2[4] == a2[4]['o'] and a2 == a2[4]['o']['a']\nstr = parse('[{\"prop\":\"1\",\"a\":\"2\",\"b\":\"3\"},{\"value\":123},[\"4\",\"5\"],{\"e\":\"6\",\"t\":\"7\",\"p\":4},{},{\"b\":\"8\"},\"f\",{\"a\":\"9\"},[\"10\"],\"sup\",{\"a\":1,\"d\":2,\"c\":\"7\",\"z\":\"11\",\"h\":1},{\"g\":2,\"a\":\"7\",\"b\":\"12\",\"f\":6},{\"r\":4,\"u\":\"7\",\"c\":5}]')\nassert str['b']['t']['a'] == 'sup' and str['a'][1]['b'][0]['c'] == str['b']['t']\noo = parse('[{\"a\":\"1\",\"b\":\"0\",\"c\":\"2\"},{\"aa\":\"3\"},{\"ca\":\"4\",\"cb\":\"5\",\"cc\":\"6\",\"cd\":\"7\",\"ce\":\"8\",\"cf\":\"9\"},{\"aaa\":\"10\"},{\"caa\":\"4\"},{\"cba\":\"5\"},{\"cca\":\"2\"},{\"cda\":\"4\"},\"value2\",\"value3\",\"value1\"]');\nassert oo['a']['aa']['aaa'] == 'value1' and oo == oo['b'] and oo['c']['ca']['caa'] == oo['c']['ca']\nprint('OK')",
        "detail": "node_modules.flatted.python.test",
        "documentation": {}
    },
    {
        "label": "str",
        "kind": 5,
        "importPath": "node_modules.flatted.python.test",
        "description": "node_modules.flatted.python.test",
        "peekOfCode": "str = parse('[{\"prop\":\"1\",\"a\":\"2\",\"b\":\"3\"},{\"value\":123},[\"4\",\"5\"],{\"e\":\"6\",\"t\":\"7\",\"p\":4},{},{\"b\":\"8\"},\"f\",{\"a\":\"9\"},[\"10\"],\"sup\",{\"a\":1,\"d\":2,\"c\":\"7\",\"z\":\"11\",\"h\":1},{\"g\":2,\"a\":\"7\",\"b\":\"12\",\"f\":6},{\"r\":4,\"u\":\"7\",\"c\":5}]')\nassert str['b']['t']['a'] == 'sup' and str['a'][1]['b'][0]['c'] == str['b']['t']\noo = parse('[{\"a\":\"1\",\"b\":\"0\",\"c\":\"2\"},{\"aa\":\"3\"},{\"ca\":\"4\",\"cb\":\"5\",\"cc\":\"6\",\"cd\":\"7\",\"ce\":\"8\",\"cf\":\"9\"},{\"aaa\":\"10\"},{\"caa\":\"4\"},{\"cba\":\"5\"},{\"cca\":\"2\"},{\"cda\":\"4\"},\"value2\",\"value3\",\"value1\"]');\nassert oo['a']['aa']['aaa'] == 'value1' and oo == oo['b'] and oo['c']['ca']['caa'] == oo['c']['ca']\nprint('OK')",
        "detail": "node_modules.flatted.python.test",
        "documentation": {}
    },
    {
        "label": "oo",
        "kind": 5,
        "importPath": "node_modules.flatted.python.test",
        "description": "node_modules.flatted.python.test",
        "peekOfCode": "oo = parse('[{\"a\":\"1\",\"b\":\"0\",\"c\":\"2\"},{\"aa\":\"3\"},{\"ca\":\"4\",\"cb\":\"5\",\"cc\":\"6\",\"cd\":\"7\",\"ce\":\"8\",\"cf\":\"9\"},{\"aaa\":\"10\"},{\"caa\":\"4\"},{\"cba\":\"5\"},{\"cca\":\"2\"},{\"cda\":\"4\"},\"value2\",\"value3\",\"value1\"]');\nassert oo['a']['aa']['aaa'] == 'value1' and oo == oo['b'] and oo['c']['ca']['caa'] == oo['c']['ca']\nprint('OK')",
        "detail": "node_modules.flatted.python.test",
        "documentation": {}
    }
]